{"type":"FeatureCollection", "features": [
{"type":"Feature","geometry":{"type":"Point","coordinates":[89.05030555555555,26.177611111111112]},"properties":{"River_Name":"Teesta","Strategic":"Teesta Barrage","Ammonia":0.47,"Arsenic":0.002,"Calcium":12,"Coliform":132,"Hrdness":638,"Lead":"0.002","Nitrogn":3.23,"Sodium":14,"Sulfate":3,"Turbidity":9.8,"Temp":25,"EC":98.2,"TSS":9,"Descriptn":"Teesta Barrage is point is located at Goddimari Union of Hatibandha Thana."}},
{"type":"Feature","geometry":{"type":"Point","coordinates":[89.104,26.005]},"properties":{"River_Name":"Teesta","Strategic":"Nohali Shapmari","Ammonia":0,"Arsenic":0,"Calcium":0,"Coliform":0,"Hrdness":0,"Lead":"","Nitrogn":0,"Sodium":0,"Sulfate":0,"Turbidity":0,"Temp":0,"EC":0,"TSS":0,"Descriptn":"Nohali is point is located at Saulmari Union of Jaldhaka Thana."}},
{"type":"Feature","geometry":{"type":"Point","coordinates":[89.43852777777778,25.788194444444446]},"properties":{"River_Name":"Teesta","Strategic":"Teesta Bridge","Ammonia":0,"Arsenic":0,"Calcium":0,"Coliform":0,"Hrdness":0,"Lead":"","Nitrogn":0,"Sodium":0,"Sulfate":0,"Turbidity":0,"Temp":0,"EC":0,"TSS":0,"Descriptn":"Teesta Bridge point is located at Gokunda union of Lalmonirhat Sadar Thana."}},
{"type":"Feature","geometry":{"type":"Point","coordinates":[89.65125,25.51833333333333]},"properties":{"River_Name":"Teesta","Strategic":"Horipur Kheya Ghat","Ammonia":0.52,"Arsenic":0.002,"Calcium":10,"Coliform":210,"Hrdness":615,"Lead":"0.003","Nitrogn":1.03,"Sodium":13,"Sulfate":3,"Turbidity":21.4,"Temp":25,"EC":94,"TSS":18,"Descriptn":"Horipur Kheya Ghat is located at Chandipur union of Sundarganj thana."}},
{"type":"Feature","geometry":{"type":"Point","coordinates":[89.58205555555556,24.89172222222222]},"properties":{"River_Name":"Jamuna","Strategic":"Sariakandi Kheya Ghat (Growin Bandh)","Ammonia":0.44,"Arsenic":0.003,"Calcium":12,"Coliform":308,"Hrdness":590,"Lead":"0.001","Nitrogn":1.62,"Sodium":16,"Sulfate":2,"Turbidity":1.85,"Temp":24.9,"EC":312,"TSS":10,"Descriptn":"Growin Bandh is located at Sariakandi union of Sariakandi Thana."}},
{"type":"Feature","geometry":{"type":"Point","coordinates":[89.81313888888889,24.662027777777777]},"properties":{"River_Name":"Jamuna","Strategic":"Tarakandi","Ammonia":0,"Arsenic":0,"Calcium":0,"Coliform":0,"Hrdness":0,"Lead":"","Nitrogn":0,"Sodium":0,"Sulfate":0,"Turbidity":0,"Temp":0,"EC":0,"TSS":0,"Descriptn":"Tarakandi location is situated at Aona union of Sarishabari Thana."}},
{"type":"Feature","geometry":{"type":"Point","coordinates":[89.75319444444445,24.399305555555554]},"properties":{"River_Name":"Jamuna","Strategic":"Jamuna Eco Park","Ammonia":0,"Arsenic":0,"Calcium":0,"Coliform":0,"Hrdness":0,"Lead":"","Nitrogn":0,"Sodium":0,"Sulfate":0,"Turbidity":0,"Temp":0,"EC":0,"TSS":0,"Descriptn":"Jamuna Eco Park is situated at Saidabad Union of Sirajganj Sadar Thana."}},
{"type":"Feature","geometry":{"type":"Point","coordinates":[89.7948611111111,24.318527777777778]},"properties":{"River_Name":"Jamuna","Strategic":"Kakua","Ammonia":0.39,"Arsenic":0.002,"Calcium":19,"Coliform":240,"Hrdness":533,"Lead":"0.001","Nitrogn":0.81,"Sodium":31,"Sulfate":12,"Turbidity":8.9,"Temp":25,"EC":214,"TSS":12,"Descriptn":"Kakua is location is situated at Kakua Union of Tangail Sadar Thana."}},
{"type":"Feature","geometry":{"type":"Point","coordinates":[89.65358333333334,24.059944444444444]},"properties":{"River_Name":"Jamuna","Strategic":"Mohonganj","Ammonia":0,"Arsenic":0,"Calcium":0,"Coliform":0,"Hrdness":0,"Lead":"","Nitrogn":0,"Sodium":0,"Sulfate":0,"Turbidity":0,"Temp":0,"EC":0,"TSS":0,"Descriptn":"Mohonganj  is  located  at  Bera Paurashava of Bera Thana."}},
{"type":"Feature","geometry":{"type":"Point","coordinates":[89.96565833333334,24.92521111111111]},"properties":{"River_Name":"Brahmaputra","Strategic":"Jamalpur Bridge","Ammonia":0,"Arsenic":0,"Calcium":0,"Coliform":0,"Hrdness":0,"Lead":"","Nitrogn":0,"Sodium":0,"Sulfate":0,"Turbidity":0,"Temp":0,"EC":0,"TSS":0,"Descriptn":"Jamalpur Bridge is located at Char Pakshimari union of Sherpur Sadar Thana."}},
{"type":"Feature","geometry":{"type":"Point","coordinates":[90.42763055555557,24.74192777777778]},"properties":{"River_Name":"Brahmaputra","Strategic":"Rail Bridge","Ammonia":0,"Arsenic":0,"Calcium":0,"Coliform":0,"Hrdness":0,"Lead":"","Nitrogn":0,"Sodium":0,"Sulfate":0,"Turbidity":0,"Temp":0,"EC":0,"TSS":0,"Descriptn":"Rail Bridge location is situated at Char Ishwardia union of Mymensingh Sadar Thana."}},
{"type":"Feature","geometry":{"type":"Point","coordinates":[91.238,25.001638888888888]},"properties":{"River_Name":"Surma","Strategic":"Jamalganj","Ammonia":0,"Arsenic":0,"Calcium":0,"Coliform":0,"Hrdness":0,"Lead":"","Nitrogn":0,"Sodium":0,"Sulfate":0,"Turbidity":0,"Temp":0,"EC":0,"TSS":0,"Descriptn":"Jamalganj is located at Jamalganj union of Jamalganj Thana in Sunamganj."}},
{"type":"Feature","geometry":{"type":"Point","coordinates":[91.39375000000001,25.07322222222222]},"properties":{"River_Name":"Surma","Strategic":"Sunamganj Lunch Ghat","Ammonia":0,"Arsenic":0,"Calcium":0,"Coliform":0,"Hrdness":0,"Lead":"","Nitrogn":0,"Sodium":0,"Sulfate":0,"Turbidity":0,"Temp":0,"EC":0,"TSS":0,"Descriptn":"Sunamganj Lunch Ghat is located at Lakshmanree union of Sunamganj Sadar Thana."}},
{"type":"Feature","geometry":{"type":"Point","coordinates":[91.67230555555555,25.033972222222225]},"properties":{"River_Name":"Surma","Strategic":"Chatak Ferry Ghat","Ammonia":0,"Arsenic":0,"Calcium":0,"Coliform":0,"Hrdness":0,"Lead":"","Nitrogn":0,"Sodium":0,"Sulfate":0,"Turbidity":0,"Temp":0,"EC":0,"TSS":0,"Descriptn":"Chatak Ferry Ghat is situated at Chatak Paurashava of Chatak Thana."}},
{"type":"Feature","geometry":{"type":"Point","coordinates":[91.87953888888889,24.88193888888889]},"properties":{"River_Name":"Surma","Strategic":"Shahjalal Bridge","Ammonia":0,"Arsenic":0,"Calcium":0,"Coliform":0,"Hrdness":0,"Lead":"","Nitrogn":0,"Sodium":0,"Sulfate":0,"Turbidity":0,"Temp":0,"EC":0,"TSS":0,"Descriptn":"Shahjalal  Bridge  is  situated  at Ward No-23 of Kotwali Thana."}},
{"type":"Feature","geometry":{"type":"Point","coordinates":[92.25886388888888,25.004069444444443]},"properties":{"River_Name":"Surma","Strategic":"Kanaighat","Ammonia":0,"Arsenic":0,"Calcium":0,"Coliform":0,"Hrdness":0,"Lead":"","Nitrogn":0,"Sodium":0,"Sulfate":0,"Turbidity":0,"Temp":0,"EC":0,"TSS":0,"Descriptn":"Kanaighatis situated  at Kanaighat union of Kanaighat Thana."}},
{"type":"Feature","geometry":{"type":"Point","coordinates":[92.15586388888889,24.85546666666667]},"properties":{"River_Name":"Kushiara","Strategic":"Bairagi Bazar","Ammonia":0,"Arsenic":0,"Calcium":0,"Coliform":0,"Hrdness":0,"Lead":"","Nitrogn":0,"Sodium":0,"Sulfate":0,"Turbidity":0,"Temp":0,"EC":0,"TSS":0,"Descriptn":"Bairagi Bazar is located at Sheola union of Beani Bazar Thana in Sylhet."}},
{"type":"Feature","geometry":{"type":"Point","coordinates":[91.90494444444445,24.654369444444445]},"properties":{"River_Name":"Kushiara","Strategic":"Fenchuganj Fertilizer Industry","Ammonia":0,"Arsenic":0,"Calcium":0,"Coliform":0,"Hrdness":0,"Lead":"","Nitrogn":0,"Sodium":0,"Sulfate":0,"Turbidity":0,"Temp":0,"EC":0,"TSS":0,"Descriptn":"Fenchuganj Fertilizer Industry is located at Uttarbhag union of Rajanagar Thana."}},
{"type":"Feature","geometry":{"type":"Point","coordinates":[90.33616944444444,23.78559166666667]},"properties":{"River_Name":"Buriganga","Strategic":"Mirpur Bridge","Ammonia":0,"Arsenic":0,"Calcium":0,"Coliform":0,"Hrdness":0,"Lead":"","Nitrogn":0,"Sodium":0,"Sulfate":0,"Turbidity":0,"Temp":0,"EC":0,"TSS":0,"Descriptn":"This location is situated at ward no. 09 (near Gabtoli) in Mirpur Thana."}},
{"type":"Feature","geometry":{"type":"Point","coordinates":[90.3451861111111,23.74312777777778]},"properties":{"River_Name":"Buriganga","Strategic":"Boshila Bridge","Ammonia":0,"Arsenic":0,"Calcium":0,"Coliform":0,"Hrdness":0,"Lead":"","Nitrogn":0,"Sodium":0,"Sulfate":0,"Turbidity":0,"Temp":0,"EC":0,"TSS":0,"Descriptn":"Boshila bridge is a location which is in Sakta Union under Keraniganj thana."}},
{"type":"Feature","geometry":{"type":"Point","coordinates":[90.3595611111111,23.721716666666666]},"properties":{"River_Name":"Buriganga","Strategic":"Hazaribagh","Ammonia":0,"Arsenic":0,"Calcium":0,"Coliform":0,"Hrdness":0,"Lead":"","Nitrogn":0,"Sodium":0,"Sulfate":0,"Turbidity":0,"Temp":0,"EC":0,"TSS":0,"Descriptn":"Hazaribagh  is  located  at  Kalindi Union under Keraniganj Thana."}},
{"type":"Feature","geometry":{"type":"Point","coordinates":[90.36852499999999,23.707963888888887]},"properties":{"River_Name":"Buriganga","Strategic":"Sata Mosque Road","Ammonia":0,"Arsenic":0,"Calcium":0,"Coliform":0,"Hrdness":0,"Lead":"","Nitrogn":0,"Sodium":0,"Sulfate":0,"Turbidity":0,"Temp":0,"EC":0,"TSS":0,"Descriptn":"This location is situated at Kalindi in Kamrangir Char."}},
{"type":"Feature","geometry":{"type":"Point","coordinates":[90.39099444444444,23.71072222222222]},"properties":{"River_Name":"Buriganga","Strategic":"Chandni Ghat","Ammonia":0.69,"Arsenic":0.002,"Calcium":12.21,"Coliform":290,"Hrdness":135,"Lead":"<LOQ","Nitrogn":35.1,"Sodium":16,"Sulfate":35,"Turbidity":10,"Temp":24.9,"EC":354,"TSS":14,"Descriptn":"Chandni Ghat is situated at Zinjira Union in Kamrangir Char Thana."}},
{"type":"Feature","geometry":{"type":"Point","coordinates":[90.42677777777779,23.68715277777778]},"properties":{"River_Name":"Buriganga","Strategic":"BD-China Friendship Bridge","Ammonia":0,"Arsenic":0,"Calcium":0,"Coliform":0,"Hrdness":0,"Lead":"","Nitrogn":0,"Sodium":0,"Sulfate":0,"Turbidity":0,"Temp":0,"EC":0,"TSS":0,"Descriptn":"Bd-China Friendship  Bridge location is situated at Subhadya union in Keraniganj."}},
{"type":"Feature","geometry":{"type":"Point","coordinates":[90.466925,23.647966666666665]},"properties":{"River_Name":"Buriganga","Strategic":"Fatullah","Ammonia":0.85,"Arsenic":0.002,"Calcium":11.1,"Coliform":382,"Hrdness":155,"Lead":"<LOQ","Nitrogn":17.6,"Sodium":15,"Sulfate":16,"Turbidity":8.5,"Temp":21.1,"EC":292,"TSS":15,"Descriptn":"This location is situated at Fatullah Union in Narayanganj Sadar Thana."}},
{"type":"Feature","geometry":{"type":"Point","coordinates":[90.36002777777777,23.8923]},"properties":{"River_Name":"Turag","Strategic":"Turag Bridge","Ammonia":0,"Arsenic":0,"Calcium":0,"Coliform":0,"Hrdness":0,"Lead":"","Nitrogn":0,"Sodium":0,"Sulfate":0,"Turbidity":0,"Temp":0,"EC":0,"TSS":0,"Descriptn":"This location is in Tongi Pourashava near Ashulia Bus Stop and Anon Text Group Industries."}},
{"type":"Feature","geometry":{"type":"Point","coordinates":[90.33938102846605,23.891681928543203]},"properties":{"River_Name":"Turag","Strategic":"Ashulia","Ammonia":0.74,"Arsenic":0.002,"Calcium":16.05,"Coliform":418,"Hrdness":130,"Lead":"0.006","Nitrogn":7.14,"Sodium":20,"Sulfate":5,"Turbidity":8.1,"Temp":25,"EC":221,"TSS":12,"Descriptn":"Ashulia point is located at Ashulia Bridge of Ashulia Union in Savar Thana."}},
{"type":"Feature","geometry":{"type":"Point","coordinates":[90.21454721801501,24.083170336645612]},"properties":{"River_Name":"Turag","Strategic":"Kaliakoir","Ammonia":0.92,"Arsenic":0.003,"Calcium":10.91,"Coliform":400,"Hrdness":125,"Lead":"<LOQ","Nitrogn":0.68,"Sodium":13,"Sulfate":24,"Turbidity":65.7,"Temp":25.1,"EC":171,"TSS":10,"Descriptn":"Kaliakoir  point  is  located  at  Sreefaltali Union of Kaliakoir Thana."}},
{"type":"Feature","geometry":{"type":"Point","coordinates":[90.34635516758374,24.03506205389942]},"properties":{"River_Name":"Turag","Strategic":"Vawal","Ammonia":0,"Arsenic":0,"Calcium":0,"Coliform":0,"Hrdness":0,"Lead":"","Nitrogn":0,"Sodium":0,"Sulfate":0,"Turbidity":0,"Temp":0,"EC":0,"TSS":0,"Descriptn":"Vawal point is located at Kayaltia Union of Gazipur Sadar Thana."}},
{"type":"Feature","geometry":{"type":"Point","coordinates":[90.32880833333333,23.98378888888889]},"properties":{"River_Name":"Turag","Strategic":"Nama Bazar","Ammonia":0,"Arsenic":0,"Calcium":0,"Coliform":0,"Hrdness":0,"Lead":"","Nitrogn":0,"Sodium":0,"Sulfate":0,"Turbidity":0,"Temp":0,"EC":0,"TSS":0,"Descriptn":"Nama Bazar is located at Kashimpur Union of Gazipur Sadar Thana. Kashimpur High School is very near to this location."}},
{"type":"Feature","geometry":{"type":"Point","coordinates":[90.51630027196855,23.62820123397404]},"properties":{"River_Name":"Shitalakhya","Strategic":"Port Road","Ammonia":0.87,"Arsenic":0.002,"Calcium":12.05,"Coliform":208,"Hrdness":155,"Lead":"0.002","Nitrogn":4.52,"Sodium":16,"Sulfate":33,"Turbidity":26,"Temp":25.2,"EC":292,"TSS":11,"Descriptn":"This location is situated at Kadam Rasul Paurashava of Bandar Thana."}},
{"type":"Feature","geometry":{"type":"Point","coordinates":[90.50309461487348,23.721413875567357]},"properties":{"River_Name":"Shitalakhya","Strategic":"Majhira (Demra Ghat)","Ammonia":0.81,"Arsenic":0.003,"Calcium":14.74,"Coliform":316,"Hrdness":138,"Lead":"0.006","Nitrogn":11.82,"Sodium":19,"Sulfate":28,"Turbidity":25.1,"Temp":24.9,"EC":317,"TSS":18,"Descriptn":"This location is situated at Tarabo Union in Rupganj Thana."}},
{"type":"Feature","geometry":{"type":"Point","coordinates":[90.52539970605869,23.79028314538161]},"properties":{"River_Name":"Shitalakhya","Strategic":"Murapara (Rupganj)","Ammonia":0,"Arsenic":0,"Calcium":0,"Coliform":0,"Hrdness":0,"Lead":"","Nitrogn":0,"Sodium":0,"Sulfate":0,"Turbidity":0,"Temp":0,"EC":0,"TSS":0,"Descriptn":"Murapara is located at Mura Para Union of Rupganj Thana."}},
{"type":"Feature","geometry":{"type":"Point","coordinates":[90.63755386509162,23.991487492771935]},"properties":{"River_Name":"Shitalakhya","Strategic":"Ghorashal Fertilizer","Ammonia":0,"Arsenic":0,"Calcium":0,"Coliform":0,"Hrdness":0,"Lead":"","Nitrogn":0,"Sodium":0,"Sulfate":0,"Turbidity":0,"Temp":0,"EC":0,"TSS":0,"Descriptn":"The point near Ghorashal Fertillizer located at Char Sindur Union of Palash Thana."}},
{"type":"Feature","geometry":{"type":"Point","coordinates":[90.51200555555556,23.569419444444446]},"properties":{"River_Name":"Dheleshwari","Strategic":"Mukterpur Bridge","Ammonia":0,"Arsenic":0,"Calcium":0,"Coliform":0,"Hrdness":0,"Lead":"","Nitrogn":0,"Sodium":0,"Sulfate":0,"Turbidity":0,"Temp":0,"EC":0,"TSS":0,"Descriptn":"Mukterpur Bridge is located at Panchasar Union in Munshiganj Sadar Thana."}},
{"type":"Feature","geometry":{"type":"Point","coordinates":[90.36237777777777,23.635644444444445]},"properties":{"River_Name":"Dheleshwari","Strategic":"Patharghata","Ammonia":0.59,"Arsenic":0.005,"Calcium":36,"Coliform":60,"Hrdness":710,"Lead":"0.01","Nitrogn":1.79,"Sodium":38,"Sulfate":9,"Turbidity":4.4,"Temp":26.1,"EC":369,"TSS":4,"Descriptn":"Patharghata is situated at Basail Union near Pathargatha Bazar (It Khola Road) and opposite of Dhaleswari Resort in Serajdikhan Thana."}},
{"type":"Feature","geometry":{"type":"Point","coordinates":[90.3096,23.66119722222222]},"properties":{"River_Name":"Dheleshwari","Strategic":"Ruhitpur (BSCIC Ind.)","Ammonia":0,"Arsenic":0,"Calcium":0,"Coliform":0,"Hrdness":0,"Lead":"","Nitrogn":0,"Sodium":0,"Sulfate":0,"Turbidity":0,"Temp":0,"EC":0,"TSS":0,"Descriptn":"This point is located at Ruhitpur union near BSCIC industrial areas in Keraniganj Thana."}},
{"type":"Feature","geometry":{"type":"Point","coordinates":[90.25131944444445,23.733219444444444]},"properties":{"River_Name":"Dheleshwari","Strategic":"Hazratpur","Ammonia":0.73,"Arsenic":0.004,"Calcium":20,"Coliform":72,"Hrdness":715,"Lead":"0.026","Nitrogn":2.76,"Sodium":24,"Sulfate":100,"Turbidity":8.3,"Temp":26,"EC":367,"TSS":4,"Descriptn":"This point is located at Hazratpur union (confluence of Kaliganga and Dhaleswari) near Alinagar in Keraniganj Thana."}},
{"type":"Feature","geometry":{"type":"Point","coordinates":[90.23755833333334,23.77214722222222]},"properties":{"River_Name":"Dheleshwari","Strategic":"Hemayetpurt CETP","Ammonia":2.2,"Arsenic":0.007,"Calcium":70,"Coliform":780,"Hrdness":360,"Lead":"0.008","Nitrogn":10.86,"Sodium":109,"Sulfate":72,"Turbidity":4.71,"Temp":24.8,"EC":642,"TSS":8,"Descriptn":"This monitoring station is located at the south-western point of Hemayetpurt CETP at Hazratpur Union of Keraniganj Thana."}},
{"type":"Feature","geometry":{"type":"Point","coordinates":[90.05461111111111,23.817722222222223]},"properties":{"River_Name":"Dheleshwari","Strategic":"Uttar Mitora","Ammonia":1.3,"Arsenic":0.007,"Calcium":43,"Coliform":860,"Hrdness":475,"Lead":"0.007","Nitrogn":0.97,"Sodium":57,"Sulfate":1,"Turbidity":2.48,"Temp":25.1,"EC":592,"TSS":7,"Descriptn":"This location is situated at Betila Mitara Union near the Martinate River’s Elementary High School in Manikganj Sadar Thana."}},
{"type":"Feature","geometry":{"type":"Point","coordinates":[90.00210833333334,23.846191666666666]},"properties":{"River_Name":"Kaliganga","Strategic":"Beutha Ghat","Ammonia":0,"Arsenic":0,"Calcium":0,"Coliform":0,"Hrdness":0,"Lead":"","Nitrogn":0,"Sodium":0,"Sulfate":0,"Turbidity":0,"Temp":0,"EC":0,"TSS":0,"Descriptn":"Beutha   Ghat   is   located   at   Manikganj Paurashava in Manikganj Sadar Thana."}},
{"type":"Feature","geometry":{"type":"Point","coordinates":[90.46279166666667,23.760158333333333]},"properties":{"River_Name":"Balu","Strategic":"Trimohini Bridge","Ammonia":0,"Arsenic":0,"Calcium":0,"Coliform":0,"Hrdness":0,"Lead":"","Nitrogn":0,"Sodium":0,"Sulfate":0,"Turbidity":0,"Temp":0,"EC":0,"TSS":0,"Descriptn":"Trimohini Bridge is located at Demra (part) in Sabujbagh Thana."}},
{"type":"Feature","geometry":{"type":"Point","coordinates":[90.48453611111111,23.812783333333336]},"properties":{"River_Name":"Balu","Strategic":"Jalshiri Abashon","Ammonia":0,"Arsenic":0,"Calcium":0,"Coliform":0,"Hrdness":0,"Lead":"","Nitrogn":0,"Sodium":0,"Sulfate":0,"Turbidity":0,"Temp":0,"EC":0,"TSS":0,"Descriptn":"Jalshiri Abashon is located at Kayet Para in Rupganj Thana."}},
{"type":"Feature","geometry":{"type":"Point","coordinates":[90.04329444444444,23.640597222222222]},"properties":{"River_Name":"Padma","Strategic":"Barha Ghat","Ammonia":0.51,"Arsenic":0.001,"Calcium":17,"Coliform":640,"Hrdness":20,"Lead":"0.006","Nitrogn":0.51,"Sodium":22,"Sulfate":11,"Turbidity":12,"Temp":25.2,"EC":216,"TSS":5,"Descriptn":"Barha Ghat is located at Nayabari union of Dohar Thana."}},
{"type":"Feature","geometry":{"type":"Point","coordinates":[90.10617777777777,23.477319444444444]},"properties":{"River_Name":"Padma","Strategic":"Nort Beak Martin Island","Ammonia":0,"Arsenic":0,"Calcium":0,"Coliform":0,"Hrdness":0,"Lead":"","Nitrogn":0,"Sodium":0,"Sulfate":0,"Turbidity":0,"Temp":0,"EC":0,"TSS":0,"Descriptn":"Nort Beak Martin Island is located near Chandrapara Trauler Ghat at Char Nasirpur Union of Sadarpur Thana."}},
{"type":"Feature","geometry":{"type":"Point","coordinates":[90.25640555555556,23.47172222222222]},"properties":{"River_Name":"Padma","Strategic":"Mawa Ghat","Ammonia":0.59,"Arsenic":0.001,"Calcium":39,"Coliform":282,"Hrdness":325,"Lead":"0.007","Nitrogn":20.36,"Sodium":41,"Sulfate":61,"Turbidity":2.1,"Temp":24.7,"EC":300,"TSS":10,"Descriptn":"Mawa Ghat is located at Medini Mandal of Lohajang Thana."}},
{"type":"Feature","geometry":{"type":"Point","coordinates":[90.64096388888889,23.22993888888889]},"properties":{"River_Name":"Padma","Strategic":"Puran Bazar","Ammonia":0,"Arsenic":0,"Calcium":0,"Coliform":0,"Hrdness":0,"Lead":"","Nitrogn":0,"Sodium":0,"Sulfate":0,"Turbidity":0,"Temp":0,"EC":0,"TSS":0,"Descriptn":"Puran Bazar at Chandpur Pourashava in Chandpur Sadar Thana."}},
{"type":"Feature","geometry":{"type":"Point","coordinates":[90.6503888888889,23.220166666666664]},"properties":{"River_Name":"Dakatia","Strategic":"Pal Bazar Bridge","Ammonia":0,"Arsenic":0,"Calcium":0,"Coliform":0,"Hrdness":0,"Lead":"","Nitrogn":0,"Sodium":0,"Sulfate":0,"Turbidity":0,"Temp":0,"EC":0,"TSS":0,"Descriptn":"Pal Bazar Bridge is located at Chandpur Paurashava of Chandpur Sadar Thana."}},
{"type":"Feature","geometry":{"type":"Point","coordinates":[90.67283333333334,23.203444444444443]},"properties":{"River_Name":"Dakatia","Strategic":"Dhali Ghat, Dakatia","Ammonia":0,"Arsenic":0,"Calcium":0,"Coliform":0,"Hrdness":0,"Lead":"","Nitrogn":0,"Sodium":0,"Sulfate":0,"Turbidity":0,"Temp":0,"EC":0,"TSS":0,"Descriptn":"Dhali Ghat is located at Sakhua union of Chandpur Sadar Thana."}},
{"type":"Feature","geometry":{"type":"Point","coordinates":[90.66925,23.225027777777775]},"properties":{"River_Name":"Dakatia","Strategic":"Gazibari Road","Ammonia":0,"Arsenic":0,"Calcium":0,"Coliform":0,"Hrdness":0,"Lead":"","Nitrogn":0,"Sodium":0,"Sulfate":0,"Turbidity":0,"Temp":0,"EC":0,"TSS":0,"Descriptn":"Gazibari Road is located at Tarpur Chandi union of Chandpur Sadar Thana."}},
{"type":"Feature","geometry":{"type":"Point","coordinates":[90.85286207795545,23.246892315111577]},"properties":{"River_Name":"Dakatia","Strategic":"Hajiganj Bazar Bridge","Ammonia":0,"Arsenic":0,"Calcium":0,"Coliform":0,"Hrdness":0,"Lead":"","Nitrogn":0,"Sodium":0,"Sulfate":0,"Turbidity":0,"Temp":0,"EC":0,"TSS":0,"Descriptn":"Hajiganj Bazar Bridge is located at Paschim Barkul union  of Chandpur Sadar Thana."}},
{"type":"Feature","geometry":{"type":"Point","coordinates":[90.61369444444443,23.60825]},"properties":{"River_Name":"Meghna","Strategic":"Meghna Ghat Power Plant","Ammonia":0.74,"Arsenic":0.002,"Calcium":26,"Coliform":118,"Hrdness":255,"Lead":"0.002","Nitrogn":2.98,"Sodium":27,"Sulfate":2,"Turbidity":3.2,"Temp":22.4,"EC":103,"TSS":7,"Descriptn":"Meghna Ghat power plant is located near Meghna Bridge at Pirijpur union of Sonargaon Thana."}},
{"type":"Feature","geometry":{"type":"Point","coordinates":[90.63705555555556,23.678722222222223]},"properties":{"River_Name":"Meghna","Strategic":"Ananda Bazar","Ammonia":0,"Arsenic":0,"Calcium":0,"Coliform":0,"Hrdness":0,"Lead":"","Nitrogn":0,"Sodium":0,"Sulfate":0,"Turbidity":0,"Temp":0,"EC":0,"TSS":0,"Descriptn":"Ananda Bazar is located at Baradi Union in Sonargaon Thana."}},
{"type":"Feature","geometry":{"type":"Point","coordinates":[90.72572222222223,23.76818611111111]},"properties":{"River_Name":"Meghna","Strategic":"Bishnandi","Ammonia":0.61,"Arsenic":0.004,"Calcium":11,"Coliform":96,"Hrdness":270,"Lead":"0.001","Nitrogn":3.62,"Sodium":14,"Sulfate":15,"Turbidity":4.7,"Temp":22,"EC":215,"TSS":12,"Descriptn":"Bishnandi is located at Bishnandi Union of Araihazar Thana."}},
{"type":"Feature","geometry":{"type":"Point","coordinates":[90.71942222222222,23.914319444444445]},"properties":{"River_Name":"Meghna","Strategic":"Narshingdi  Launch Terminal","Ammonia":0,"Arsenic":0,"Calcium":0,"Coliform":0,"Hrdness":0,"Lead":"","Nitrogn":0,"Sodium":0,"Sulfate":0,"Turbidity":0,"Temp":0,"EC":0,"TSS":0,"Descriptn":"Narshingdi Launch Terminal is located in Narshingdi Pourashava in Narshingdi Sadar Thana."}},
{"type":"Feature","geometry":{"type":"Point","coordinates":[90.98976111111111,24.043375]},"properties":{"River_Name":"Meghna","Strategic":"Bhairab bazar","Ammonia":0,"Arsenic":0,"Calcium":0,"Coliform":0,"Hrdness":0,"Lead":"","Nitrogn":0,"Sodium":0,"Sulfate":0,"Turbidity":0,"Temp":0,"EC":0,"TSS":0,"Descriptn":"Bhairabbazar is located at Bhairab bazar Pourashava in Bhairab Thana."}},
{"type":"Feature","geometry":{"type":"Point","coordinates":[91.17755833333334,24.045169444444447]},"properties":{"River_Name":"Titas","Strategic":"Bakail Bridge (Titas)","Ammonia":0,"Arsenic":0,"Calcium":0,"Coliform":0,"Hrdness":0,"Lead":"","Nitrogn":0,"Sodium":0,"Sulfate":0,"Turbidity":0,"Temp":0,"EC":0,"TSS":0,"Descriptn":"Bakail Bridge is located at Shahbazpur union  of Sarail Thana in Brahmanbaria district."}},
{"type":"Feature","geometry":{"type":"Point","coordinates":[91.20000833333333,23.878747222222223]},"properties":{"River_Name":"Titas","Strategic":"Titas Rail Bridge","Ammonia":0,"Arsenic":0,"Calcium":0,"Coliform":0,"Hrdness":0,"Lead":"","Nitrogn":0,"Sodium":0,"Sulfate":0,"Turbidity":0,"Temp":0,"EC":0,"TSS":0,"Descriptn":"Titas Rail Bridge is located at Akhaura Paurashava of Akhaura Thana in Brahmanbaria district."}},
{"type":"Feature","geometry":{"type":"Point","coordinates":[89.37394166666667,24.854883333333333]},"properties":{"River_Name":"Karatoya","Strategic":"Dottobari Bridge","Ammonia":0,"Arsenic":0,"Calcium":0,"Coliform":0,"Hrdness":0,"Lead":"","Nitrogn":0,"Sodium":0,"Sulfate":0,"Turbidity":0,"Temp":0,"EC":0,"TSS":0,"Descriptn":"Dottobari Bridge is located at Shabgram union of Bogra Sadar Thana."}},
{"type":"Feature","geometry":{"type":"Point","coordinates":[89.38176666666666,24.843616666666666]},"properties":{"River_Name":"Karatoya","Strategic":"Aziz Ahmed Taki Road","Ammonia":0,"Arsenic":0,"Calcium":0,"Coliform":0,"Hrdness":0,"Lead":"","Nitrogn":0,"Sodium":0,"Sulfate":0,"Turbidity":0,"Temp":0,"EC":0,"TSS":0,"Descriptn":"Aziz Ahmed Taki Road is located at Shabgram union of Bogra Sadar Thana."}},
{"type":"Feature","geometry":{"type":"Point","coordinates":[89.40692222222222,24.801372222222223]},"properties":{"River_Name":"Karatoya","Strategic":"Sultanganj- Gabtoli Road","Ammonia":0,"Arsenic":0,"Calcium":0,"Coliform":0,"Hrdness":0,"Lead":"","Nitrogn":0,"Sodium":0,"Sulfate":0,"Turbidity":0,"Temp":0,"EC":0,"TSS":0,"Descriptn":"Sultanaganj Gabtoli Road is located at Madla union of Bogra Sadar Thana."}},
{"type":"Feature","geometry":{"type":"Point","coordinates":[88.7265325609815,24.299686320232038]},"properties":{"River_Name":"Ganges","Strategic":"Sardah","Ammonia":0.61,"Arsenic":0.003,"Calcium":39,"Coliform":192,"Hrdness":685,"Lead":"0.004","Nitrogn":2.1,"Sodium":47,"Sulfate":8,"Turbidity":42.7,"Temp":24.9,"EC":275,"TSS":13,"Descriptn":"Sardah point is located at Harian union of Paba Thana."}},
{"type":"Feature","geometry":{"type":"Point","coordinates":[88.99280555555556,24.16825]},"properties":{"River_Name":"Ganges","Strategic":"Nurullapur","Ammonia":0,"Arsenic":0,"Calcium":0,"Coliform":0,"Hrdness":0,"Lead":"","Nitrogn":0,"Sodium":0,"Sulfate":0,"Turbidity":0,"Temp":0,"EC":0,"TSS":0,"Descriptn":"Nurullapur  is  located  at  Ishwardi union of Lalpur Thana."}},
{"type":"Feature","geometry":{"type":"Point","coordinates":[89.1108611111111,23.950666666666667]},"properties":{"River_Name":"Ganges","Strategic":"Gorai Off Take","Ammonia":0.43,"Arsenic":0.003,"Calcium":19,"Coliform":102,"Hrdness":463,"Lead":"0.003","Nitrogn":2.51,"Sodium":21,"Sulfate":7,"Turbidity":11.6,"Temp":25,"EC":275,"TSS":11,"Descriptn":"Gorai Off Take is located at Hatash Haripur union of Kushtia Sadar Thana."}},
{"type":"Feature","geometry":{"type":"Point","coordinates":[88.99280555555556,24.16825]},"properties":{"River_Name":"Ganges","Strategic":"Kanchan Park","Ammonia":0,"Arsenic":0,"Calcium":0,"Coliform":0,"Hrdness":0,"Lead":"","Nitrogn":0,"Sodium":0,"Sulfate":0,"Turbidity":0,"Temp":0,"EC":0,"TSS":0,"Descriptn":"Kanchan park is located at Ishwardi union of Lalpur Thana."}},
{"type":"Feature","geometry":{"type":"Point","coordinates":[89.52990108752245,23.53609011206806]},"properties":{"River_Name":"Gorai River","Strategic":"Kamarkhali Bridge","Ammonia":0,"Arsenic":0,"Calcium":0,"Coliform":0,"Hrdness":0,"Lead":"","Nitrogn":0,"Sodium":0,"Sulfate":0,"Turbidity":0,"Temp":0,"EC":0,"TSS":0,"Descriptn":"Kamarkhali Bridge is located at Nakol union of Sreepur thana in Magura."}},
{"type":"Feature","geometry":{"type":"Point","coordinates":[89.67796111111112,23.138827777777777]},"properties":{"River_Name":"Modhumoti River","Strategic":"Dhalaitala","Ammonia":0,"Arsenic":0,"Calcium":0,"Coliform":0,"Hrdness":0,"Lead":"","Nitrogn":0,"Sodium":0,"Sulfate":0,"Turbidity":0,"Temp":0,"EC":0,"TSS":0,"Descriptn":"Dhalaitala point is located at Kotakul union of lohagara thana in Narail."}},
{"type":"Feature","geometry":{"type":"Point","coordinates":[89.89555256793791,22.8811281018426]},"properties":{"River_Name":"Modhumoti River","Strategic":"Patgati- Nazimpur","Ammonia":0,"Arsenic":0,"Calcium":0,"Coliform":0,"Hrdness":0,"Lead":"","Nitrogn":0,"Sodium":0,"Sulfate":0,"Turbidity":0,"Temp":0,"EC":0,"TSS":0,"Descriptn":"Patgati - Nazimpur point is located at Ptagati Union of Tungipara Thana."}},
{"type":"Feature","geometry":{"type":"Point","coordinates":[88.78897222222221,23.523688888888888]},"properties":{"River_Name":"Mathavanga River","Strategic":"Dorshona Railway Junction","Ammonia":0,"Arsenic":0,"Calcium":0,"Coliform":0,"Hrdness":0,"Lead":"","Nitrogn":0,"Sodium":0,"Sulfate":0,"Turbidity":0,"Temp":0,"EC":0,"TSS":0,"Descriptn":"Kamarkhali Bridge is located at Darshana Paurashava of Damurhuda thana in Chuadanga."}},
{"type":"Feature","geometry":{"type":"Point","coordinates":[89.03384444444444,22.457727777777777]},"properties":{"River_Name":"Kankshiali River","Strategic":"Kaliganj   Bazar Bridge","Ammonia":0,"Arsenic":0,"Calcium":0,"Coliform":0,"Hrdness":0,"Lead":"","Nitrogn":0,"Sodium":0,"Sulfate":0,"Turbidity":0,"Temp":0,"EC":0,"TSS":0,"Descriptn":"Kaliganj Bazar Bridge is located at Tarali union of Kaliganj thana in Stakhira."}},
{"type":"Feature","geometry":{"type":"Point","coordinates":[89.00584444444445,22.473149999999997]},"properties":{"River_Name":"Kankshiali River","Strategic":"Boshontopur","Ammonia":0,"Arsenic":0,"Calcium":0,"Coliform":0,"Hrdness":0,"Lead":"","Nitrogn":0,"Sodium":0,"Sulfate":0,"Turbidity":0,"Temp":0,"EC":0,"TSS":0,"Descriptn":"Kaliganj Bazar Bridge is located at Barha Simla union of Kaliganj thana in Stakhira."}},
{"type":"Feature","geometry":{"type":"Point","coordinates":[89.1274,22.512525]},"properties":{"River_Name":"Kankshiali River","Strategic":"Uzirpur, Gobindakathi","Ammonia":0,"Arsenic":0,"Calcium":0,"Coliform":0,"Hrdness":0,"Lead":"","Nitrogn":0,"Sodium":0,"Sulfate":0,"Turbidity":0,"Temp":0,"EC":0,"TSS":0,"Descriptn":"Uzirpur, Gobindakathi is located at Champaphul union of Kaliganj thana in Stakhira."}},
{"type":"Feature","geometry":{"type":"Point","coordinates":[89.36913888888888,23.137433333333334]},"properties":{"River_Name":"Bhairab River","Strategic":"Bashundia Bazar","Ammonia":0,"Arsenic":0,"Calcium":0,"Coliform":0,"Hrdness":0,"Lead":"","Nitrogn":0,"Sodium":0,"Sulfate":0,"Turbidity":0,"Temp":0,"EC":0,"TSS":0,"Descriptn":"Bashundia Bazar point is located at Basuari union of Bagher Para Thana."}},
{"type":"Feature","geometry":{"type":"Point","coordinates":[89.39500549210295,23.03603041237427]},"properties":{"River_Name":"Bhairab River","Strategic":"Noapara Ferry Ghat","Ammonia":0,"Arsenic":0,"Calcium":0,"Coliform":0,"Hrdness":0,"Lead":"","Nitrogn":0,"Sodium":0,"Sulfate":0,"Turbidity":0,"Temp":0,"EC":0,"TSS":0,"Descriptn":"Noapara Ferry Ghat point is located at Abhaynagar Paurashava of Abhaynagar Thana."}},
{"type":"Feature","geometry":{"type":"Point","coordinates":[89.41600833333334,23.0117]},"properties":{"River_Name":"Bhairab River","Strategic":"Taltola, Noapara","Ammonia":0,"Arsenic":0,"Calcium":0,"Coliform":0,"Hrdness":0,"Lead":"","Nitrogn":0,"Sodium":0,"Sulfate":0,"Turbidity":0,"Temp":0,"EC":0,"TSS":0,"Descriptn":"Taltola point is located at Abhaynagar Paurashava of Abhaynagar Thana."}},
{"type":"Feature","geometry":{"type":"Point","coordinates":[89.47813611111111,22.97743333333333]},"properties":{"River_Name":"Bhairab River","Strategic":"Fultala Ghat","Ammonia":0,"Arsenic":0,"Calcium":0,"Coliform":0,"Hrdness":0,"Lead":"","Nitrogn":0,"Sodium":0,"Sulfate":0,"Turbidity":0,"Temp":0,"EC":0,"TSS":0,"Descriptn":"Fultala Ghat point is located at Siddhipasha Union of Abhaynagar Thana."}},
{"type":"Feature","geometry":{"type":"Point","coordinates":[89.5147861111111,22.927622222222222]},"properties":{"River_Name":"Rupsha River","Strategic":"Gilatala","Ammonia":0.82,"Arsenic":0.003,"Calcium":69,"Coliform":404,"Hrdness":350,"Lead":"0.004","Nitrogn":2.15,"Sodium":73,"Sulfate":7,"Turbidity":80,"Temp":24.8,"EC":570,"TSS":26,"Descriptn":"Gilatala point is located at Barakpur union of Digohalia Thana."}},
{"type":"Feature","geometry":{"type":"Point","coordinates":[89.56027947448844,22.847830742039832]},"properties":{"River_Name":"Rupsha River","Strategic":"Charer Hat","Ammonia":0,"Arsenic":0,"Calcium":0,"Coliform":0,"Hrdness":0,"Lead":"","Nitrogn":0,"Sodium":0,"Sulfate":0,"Turbidity":0,"Temp":0,"EC":0,"TSS":0,"Descriptn":"Charer Hat point is located at Aijganti Union of Rupsha Thana."}},
{"type":"Feature","geometry":{"type":"Point","coordinates":[89.57178958154509,22.81991124829087]},"properties":{"River_Name":"Rupsha River","Strategic":"Kalibari Ghat","Ammonia":0.7,"Arsenic":0.002,"Calcium":24,"Coliform":320,"Hrdness":310,"Lead":"0.009","Nitrogn":0.93,"Sodium":29,"Sulfate":4,"Turbidity":27.7,"Temp":25,"EC":350,"TSS":15,"Descriptn":"Kalibari Ghat point is located at Aijganti Union of Rupsha Thana."}},
{"type":"Feature","geometry":{"type":"Point","coordinates":[89.58706271596698,22.788365685886593]},"properties":{"River_Name":"Rupsha River","Strategic":"Rupsha Ghat (Old)","Ammonia":0.62,"Arsenic":0.002,"Calcium":48,"Coliform":242,"Hrdness":310,"Lead":"0.003","Nitrogn":0.87,"Sodium":51,"Sulfate":5,"Turbidity":46.7,"Temp":24.8,"EC":350,"TSS":12,"Descriptn":"Rupsha Ghat (Old) point is located at Naihati Union of Rupsha Thana."}},
{"type":"Feature","geometry":{"type":"Point","coordinates":[89.52989196263688,22.748784992368876]},"properties":{"River_Name":"Moyuri River","Strategic":"Shashan Ghat","Ammonia":0.86,"Arsenic":0.003,"Calcium":147,"Coliform":380,"Hrdness":540,"Lead":"0.014","Nitrogn":0.64,"Sodium":162,"Sulfate":10,"Turbidity":6.5,"Temp":24.8,"EC":1232,"TSS":31,"Descriptn":"Shashan Ghat point  is located at Jalma union of Batiaghata Thana."}},
{"type":"Feature","geometry":{"type":"Point","coordinates":[89.5432,22.796666666666667]},"properties":{"River_Name":"Moyuri River","Strategic":"Buro Moulavir Darga","Ammonia":0.78,"Arsenic":0.002,"Calcium":165,"Coliform":182,"Hrdness":475,"Lead":"0.01","Nitrogn":0.39,"Sodium":178,"Sulfate":3,"Turbidity":2.9,"Temp":24.9,"EC":1320,"TSS":25,"Descriptn":"Buro Moulavir Darga point is located at Jalma Union of Batiaghata Thana."}},
{"type":"Feature","geometry":{"type":"Point","coordinates":[89.5513611111111,22.758222222222223]},"properties":{"River_Name":"Moyuri River","Strategic":"Dosh Gate","Ammonia":0.61,"Arsenic":0.001,"Calcium":138,"Coliform":240,"Hrdness":425,"Lead":"0.004","Nitrogn":3.11,"Sodium":129,"Sulfate":15,"Turbidity":16.3,"Temp":24.7,"EC":930,"TSS":20,"Descriptn":"Dosh Gate is point is located at Jalma Union in Batiaghata thana."}},
{"type":"Feature","geometry":{"type":"Point","coordinates":[89.52166944444444,22.742397222222223]},"properties":{"River_Name":"Pashur","Strategic":"Kazibacha- Batiaghata Bypass","Ammonia":0,"Arsenic":0,"Calcium":0,"Coliform":0,"Hrdness":0,"Lead":"","Nitrogn":0,"Sodium":0,"Sulfate":0,"Turbidity":0,"Temp":0,"EC":0,"TSS":0,"Descriptn":"Kazibacha-Batiaghata Bypass point is located at Batiaghata union of Batiaghata Thana."}},
{"type":"Feature","geometry":{"type":"Point","coordinates":[89.54906388888888,22.583322222222222]},"properties":{"River_Name":"Pashur","Strategic":"Rampal  Power Plant","Ammonia":0,"Arsenic":0,"Calcium":0,"Coliform":0,"Hrdness":0,"Lead":"","Nitrogn":0,"Sodium":0,"Sulfate":0,"Turbidity":0,"Temp":0,"EC":0,"TSS":0,"Descriptn":"Rampal Power Plant Location is situated at Rajnagar union in Rampal Thana."}},
{"type":"Feature","geometry":{"type":"Point","coordinates":[89.59036388888889,22.466497222222223]},"properties":{"River_Name":"Pashur","Strategic":"Banishanta","Ammonia":0,"Arsenic":0,"Calcium":0,"Coliform":0,"Hrdness":0,"Lead":"","Nitrogn":0,"Sodium":0,"Sulfate":0,"Turbidity":0,"Temp":0,"EC":0,"TSS":0,"Descriptn":"Banishanta point is located at Banishanta union of Dacope Thana."}},
{"type":"Feature","geometry":{"type":"Point","coordinates":[90.177875,22.62745277777778]},"properties":{"River_Name":"Sughandha","Strategic":"Gab Khan Lunch Terminal","Ammonia":0,"Arsenic":0,"Calcium":0,"Coliform":0,"Hrdness":0,"Lead":"","Nitrogn":0,"Sodium":0,"Sulfate":0,"Turbidity":0,"Temp":0,"EC":0,"TSS":0,"Descriptn":"Gab Khan Lunch Terminal is located at Gabkhan Dhansiri union of Jhalokati Sadar Thana in Jhalokati."}},
{"type":"Feature","geometry":{"type":"Point","coordinates":[90.34328987767876,22.64456556185608]},"properties":{"River_Name":"Kirtankhola","Strategic":"Dopdopia Kheya Ghat","Ammonia":0,"Arsenic":0,"Calcium":0,"Coliform":0,"Hrdness":0,"Lead":"","Nitrogn":0,"Sodium":0,"Sulfate":0,"Turbidity":0,"Temp":0,"EC":0,"TSS":0,"Descriptn":"Dapdopia Khea Ghat point is located at Dapdapia union of Nalchity Thana in Jhalokati."}},
{"type":"Feature","geometry":{"type":"Point","coordinates":[90.37874989198744,22.696961256420753]},"properties":{"River_Name":"Kirtankhola","Strategic":"Kauar Char Ferry Ghat","Ammonia":0,"Arsenic":0,"Calcium":0,"Coliform":0,"Hrdness":0,"Lead":"","Nitrogn":0,"Sodium":0,"Sulfate":0,"Turbidity":0,"Temp":0,"EC":0,"TSS":0,"Descriptn":"Kauar Char Ferry Ghat Location is situated at Char Kowa union of Barisal Sadar Thana."}},
{"type":"Feature","geometry":{"type":"Point","coordinates":[90.56430360027947,22.704996857067886]},"properties":{"River_Name":"Tetulia","Strategic":"Vheduria Ferry Ghat","Ammonia":0,"Arsenic":0,"Calcium":0,"Coliform":0,"Hrdness":0,"Lead":"","Nitrogn":0,"Sodium":0,"Sulfate":0,"Turbidity":0,"Temp":0,"EC":0,"TSS":0,"Descriptn":"Vheduria ferry ghatpoint is located at Vheduria union of Bhola SadarThana."}},
{"type":"Feature","geometry":{"type":"Point","coordinates":[91.82811111111111,22.238777777777777]},"properties":{"River_Name":"Karnaphuli","Strategic":"CUFL","Ammonia":0.87,"Arsenic":0.001,"Calcium":196,"Coliform":680,"Hrdness":5800,"Lead":"0.002","Nitrogn":1.95,"Sodium":1277,"Sulfate":960,"Turbidity":143,"Temp":24.1,"EC":4226,"TSS":34,"Descriptn":"CUFL point is located at Bairag union of Karnaphuli Thana."}},
{"type":"Feature","geometry":{"type":"Point","coordinates":[91.80119444444445,22.275666666666666]},"properties":{"River_Name":"Karnaphuli","Strategic":"TSP Location","Ammonia":0,"Arsenic":0,"Calcium":0,"Coliform":0,"Hrdness":0,"Lead":"","Nitrogn":0,"Sodium":0,"Sulfate":0,"Turbidity":0,"Temp":0,"EC":0,"TSS":0,"Descriptn":"TSP Location is situated at Ward No. 40 in Patenga Thana."}},
{"type":"Feature","geometry":{"type":"Point","coordinates":[91.86866666666666,22.321444444444445]},"properties":{"River_Name":"Karnaphuli","Strategic":"Shikalbaha Power Station","Ammonia":0.72,"Arsenic":0.001,"Calcium":90,"Coliform":310,"Hrdness":195,"Lead":"0.079","Nitrogn":2.05,"Sodium":107,"Sulfate":5,"Turbidity":117,"Temp":24.4,"EC":258,"TSS":30,"Descriptn":"Shikalbaha Power Station point is located at Sikalbaha union of Karnaphuli Thana."}},
{"type":"Feature","geometry":{"type":"Point","coordinates":[91.89219444444446,22.403333333333332]},"properties":{"River_Name":"Karnaphuli","Strategic":"Kalurghat Bridge","Ammonia":0.55,"Arsenic":0.001,"Calcium":21,"Coliform":230,"Hrdness":155,"Lead":"0.005","Nitrogn":2.68,"Sodium":29,"Sulfate":3,"Turbidity":12,"Temp":24.2,"EC":103,"TSS":17,"Descriptn":"Kalurghat Bridge point is located at Ward no-05 of Chandgaon Thana."}},
{"type":"Feature","geometry":{"type":"Point","coordinates":[92.07875,22.449694444444443]},"properties":{"River_Name":"Karnaphuli","Strategic":"Mariam Nagar","Ammonia":0,"Arsenic":0,"Calcium":0,"Coliform":0,"Hrdness":0,"Lead":"","Nitrogn":0,"Sodium":0,"Sulfate":0,"Turbidity":0,"Temp":0,"EC":0,"TSS":0,"Descriptn":"Mariam Nagar point is located at Dakshin Madarsha union in Hathazari Thana."}},
{"type":"Feature","geometry":{"type":"Point","coordinates":[92.13897222222222,22.471638888888886]},"properties":{"River_Name":"Karnaphuli","Strategic":"Karnaphuli Paper Mills (KPM)","Ammonia":0.58,"Arsenic":0.001,"Calcium":32,"Coliform":412,"Hrdness":185,"Lead":"0.023","Nitrogn":2,"Sodium":38,"Sulfate":4,"Turbidity":4,"Temp":24.2,"EC":115,"TSS":15,"Descriptn":"Karnaphuli Paper Mills (KPM) point is located near the Kapti Lake at Raikhali union of Kaptai Thana."}},
{"type":"Feature","geometry":{"type":"Point","coordinates":[91.87222222222222,22.435]},"properties":{"River_Name":"Halda","Strategic":"Maduna Ghat","Ammonia":0,"Arsenic":0,"Calcium":0,"Coliform":0,"Hrdness":0,"Lead":"","Nitrogn":0,"Sodium":0,"Sulfate":0,"Turbidity":0,"Temp":0,"EC":0,"TSS":0,"Descriptn":"Maduna Ghat point is located at Dakhin Madarsha Union of Hathazari Thana."}},
{"type":"Feature","geometry":{"type":"Point","coordinates":[91.87117924702697,22.502311419821087]},"properties":{"River_Name":"Halda","Strategic":"Garduara  Sluice Gate","Ammonia":0,"Arsenic":0,"Calcium":0,"Coliform":0,"Hrdness":0,"Lead":"","Nitrogn":0,"Sodium":0,"Sulfate":0,"Turbidity":0,"Temp":0,"EC":0,"TSS":0,"Descriptn":"Garduara Sluice gate is located at Garduara union of Hathazari thana."}},
{"type":"Feature","geometry":{"type":"Point","coordinates":[91.84566666666666,22.51488888888889]},"properties":{"River_Name":"Halda","Strategic":"Halda Bridge","Ammonia":0.49,"Arsenic":0.001,"Calcium":48,"Coliform":460,"Hrdness":150,"Lead":"0.002","Nitrogn":3.08,"Sodium":48,"Sulfate":2,"Turbidity":55,"Temp":24.5,"EC":149,"TSS":28,"Descriptn":"Halda  Bridge  point  is  located  at Gahira union of Raozan thana."}}
]}